pykobo/__init__.py
pykobo/__version__.py
pykobo/features.py
pykobo/form.py
pykobo/manager.py
pykobo/utility.py
pykobo-0.1.6.dist-info/LICENSE
pykobo-0.1.6.dist-info/WHEEL
pykobo-0.1.6.dist-info/METADATA
pykobo-0.1.6.dist-info/RECORD
