Metadata-Version: 2.1
Name: pykobo
Version: 0.1.6
Summary: A Python module to fetch data from the Kobo API
Author: pvernier
Author-email: pvernier82@gmail.com
Requires-Python: >=3.8,<4.0
Classifier: Programming Language :: Python :: 3
Classifier: Programming Language :: Python :: 3.8
Classifier: Programming Language :: Python :: 3.9
Classifier: Programming Language :: Python :: 3.10
Classifier: Programming Language :: Python :: 3.11
Requires-Dist: pandas (>=1.5.1,<2.0.0)
Requires-Dist: requests (>=2.28.1,<3.0.0)
